{
  "project_info": {
    "project_number": "551379171312",
    "project_id": "remote-projector-fc831",
    "storage_bucket": "remote-projector-fc831.appspot.com"
  },
  "client": [
    {
      "client_info": {
        "mobilesdk_app_id": "1:551379171312:android:cb3007eddcd823b7238f35",
        "android_client_info": {
          "package_name": "com.example.play_box"
        }
      },
      "oauth_client": [],
      "api_key": [
        {
          "current_key": "AIzaSyBR28VwToRmJtXDsIDZyet3uqmiDEZpsnM"
        }
      ],
      "services": {
        "appinvite_service": {
          "other_platform_oauth_client": []
        }
      }
    }
  ],
  "configuration_version": "1"
}